whisperchain/cli/run.py
whisperchain/cli/run_client.py
whisperchain/cli/run_server.py
whisperchain/client/key_listener.py
whisperchain/client/stream_client.py
whisperchain/core/__init__.py
whisperchain/core/audio.py
whisperchain/core/chain.py
whisperchain/core/config.py
whisperchain/server/__init__.py
whisperchain/server/server.py
whisperchain/utils/decorators.py
whisperchain/utils/logger.py
whisperchain/utils/secrets.py
whisperchain/utils/segment.py
whisperchain-0.1.2.dist-info/LICENSE
whisperchain-0.1.2.dist-info/METADATA
whisperchain-0.1.2.dist-info/WHEEL
whisperchain-0.1.2.dist-info/entry_points.txt
whisperchain-0.1.2.dist-info/top_level.txt
whisperchain-0.1.2.dist-info/RECORD
