Metadata-Version: 2.2
Name: whisperchain
Version: 0.1.2
Summary: Voice control using Whisper.cpp with LangChain cleanup
Author-email: Chris Choy <chrischoy@ai.stanford.edu>
License: MIT
Project-URL: Homepage, https://github.com/chrischoy/whisperchain
Project-URL: Bug Tracker, https://github.com/chrischoy/whisperchain/issues
Keywords: whisper,langchain,voice-control,speech-to-text
Classifier: Development Status :: 3 - Alpha
Classifier: Intended Audience :: Developers
Classifier: License :: OSI Approved :: MIT License
Classifier: Programming Language :: Python :: 3
Classifier: Programming Language :: Python :: 3.8
Classifier: Programming Language :: Python :: 3.9
Classifier: Programming Language :: Python :: 3.10
Classifier: Topic :: Software Development :: Libraries :: Python Modules
Classifier: Topic :: Multimedia :: Sound/Audio :: Speech
Requires-Python: >=3.8
License-File: LICENSE
Requires-Dist: click>=8.0.0
Requires-Dist: pydantic>=2.0.0
Requires-Dist: pynput>=1.7.7
Requires-Dist: pyperclip
Requires-Dist: openai>=1.0.0
Requires-Dist: pywhispercpp>=1.3.0
Requires-Dist: fastapi>=0.100.0
Requires-Dist: uvicorn>=0.22.0
Requires-Dist: pyaudio>=0.2.11
Requires-Dist: langchain>=0.1.0
Requires-Dist: langchain-openai>=0.1.0
Requires-Dist: websockets>=11.0.0
Provides-Extra: test
Requires-Dist: pytest>=7.0.0; extra == "test"
Requires-Dist: pytest-asyncio>=0.21.0; extra == "test"
Requires-Dist: httpx>=0.24.0; extra == "test"
Provides-Extra: dev
Requires-Dist: pre-commit>=3.0.0; extra == "dev"
Requires-Dist: black>=22.0.0; extra == "dev"
Requires-Dist: isort>=5.0.0; extra == "dev"
Requires-Dist: build>=0.10.0; extra == "dev"
Requires-Dist: twine>=4.0.0; extra == "dev"
